Metadata-Version: 1.1
Name: typograph
Version: 0.1.0
Summary: Automatically fix typography mistakes that are commonly done when writing content on the web
Home-page: https://github.com/sephii/typograph
Author: Sylvain Fankhauser
Author-email: sylvain.fankhauser@gmail.com
License: bsd
Platform: UNKNOWN
Classifier: Environment :: Console
Classifier: Development Status :: 5 - Production/Stable
Classifier: Programming Language :: Python :: 2.7
Classifier: Programming Language :: Python :: 3.4
Classifier: Programming Language :: Python :: 3.5
